{
  "professores": [
    {
      "id": 1,
      "nome": "Erick"
    },
    {
      "id": 2,
      "nome": "Vinicius"
    },
    {
      "id": 3,
      "nome": "Santos"
    }
  ],
  "alunos": [
    {
      "id": 1,
      "nome": "testando",
      "sobrenome": "teste",
      "dataNasc": "19/12/1999",
      "professor": {
        "id": 3,
        "nome": "Santos"
      }
    },
    {
      "nome": "teste",
      "sobrenome": "",
      "id": 2,
      "professor": {
        "id": 2,
        "nome": "Vinicius"
      }
    },
    {
      "nome": "lima",
      "sobrenome": "",
      "professor": {
        "id": 3,
        "nome": "Santos"
      },
      "id": 4
    },
    {
      "nome": "Gabriel",
      "sobrenome": "",
      "professor": {
        "id": 1,
        "nome": "Erick"
      },
      "id": 5
    },
    {
      "nome": "cibele",
      "sobrenome": "",
      "professor": {
        "id": 1,
        "nome": "Erick"
      },
      "id": 6
    }
  ]
}